veesion/ClassificationModule.py
veesion/ColorModule.py
veesion/FPS.py
veesion/FaceDetectionModule.py
veesion/FaceMeshModule.py
veesion/HandTrackingModule.py
veesion/PIDModule.py
veesion/PlotModule.py
veesion/PoseModule.py
veesion/SelfiSegmentationModule.py
veesion/SerialModule.py
veesion/Utils.py
veesion/__init__.py
veesion-0.1.dist-info/METADATA
veesion-0.1.dist-info/WHEEL
veesion-0.1.dist-info/top_level.txt
veesion-0.1.dist-info/RECORD
